{"errors":[],"warnings":[],"namedChunkGroups":{"app":{"chunks":[8,0,7,2],"assets":["webpack-runtime-fa6e39bb8e101a10e86c.js","webpack-runtime-fa6e39bb8e101a10e86c.js.map","styles.5478f1c14286ecfac51c.css","styles-89fd2ae28bdf06750a71.js","styles-89fd2ae28bdf06750a71.js.map","framework-5fc6169171e885c3b522.js","framework-5fc6169171e885c3b522.js.map","app-2588892a82841f2253a6.js","app-2588892a82841f2253a6.js.map"],"children":{},"childAssets":{}},"component---src-pages-404-js":{"chunks":[0,1,3],"assets":["styles.5478f1c14286ecfac51c.css","styles-89fd2ae28bdf06750a71.js","styles-89fd2ae28bdf06750a71.js.map","commons-e8dca2748e39fa297292.js","commons-e8dca2748e39fa297292.js.map","component---src-pages-404-js-4c9fa5790aa9ec081a1b.js","component---src-pages-404-js-4c9fa5790aa9ec081a1b.js.map"],"children":{},"childAssets":{}},"component---src-pages-blog-js":{"chunks":[0,1,4],"assets":["styles.5478f1c14286ecfac51c.css","styles-89fd2ae28bdf06750a71.js","styles-89fd2ae28bdf06750a71.js.map","commons-e8dca2748e39fa297292.js","commons-e8dca2748e39fa297292.js.map","component---src-pages-blog-js-77a45f36ec71dc3dd732.js","component---src-pages-blog-js-77a45f36ec71dc3dd732.js.map"],"children":{},"childAssets":{}},"component---src-pages-index-js":{"chunks":[0,1,5],"assets":["styles.5478f1c14286ecfac51c.css","styles-89fd2ae28bdf06750a71.js","styles-89fd2ae28bdf06750a71.js.map","commons-e8dca2748e39fa297292.js","commons-e8dca2748e39fa297292.js.map","component---src-pages-index-js-20f4accd0ed20fe28911.js","component---src-pages-index-js-20f4accd0ed20fe28911.js.map"],"children":{},"childAssets":{}},"component---src-templates-normal-page-js":{"chunks":[0,1,6],"assets":["styles.5478f1c14286ecfac51c.css","styles-89fd2ae28bdf06750a71.js","styles-89fd2ae28bdf06750a71.js.map","commons-e8dca2748e39fa297292.js","commons-e8dca2748e39fa297292.js.map","component---src-templates-normal-page-js-fc5e8da66e25859a5b39.js","component---src-templates-normal-page-js-fc5e8da66e25859a5b39.js.map"],"children":{},"childAssets":{}}},"assetsByChunkName":{"app":["webpack-runtime-fa6e39bb8e101a10e86c.js","styles.5478f1c14286ecfac51c.css","styles-89fd2ae28bdf06750a71.js","framework-5fc6169171e885c3b522.js","app-2588892a82841f2253a6.js"],"component---src-pages-404-js":["styles.5478f1c14286ecfac51c.css","styles-89fd2ae28bdf06750a71.js","commons-e8dca2748e39fa297292.js","component---src-pages-404-js-4c9fa5790aa9ec081a1b.js"],"component---src-pages-blog-js":["styles.5478f1c14286ecfac51c.css","styles-89fd2ae28bdf06750a71.js","commons-e8dca2748e39fa297292.js","component---src-pages-blog-js-77a45f36ec71dc3dd732.js"],"component---src-pages-index-js":["styles.5478f1c14286ecfac51c.css","styles-89fd2ae28bdf06750a71.js","commons-e8dca2748e39fa297292.js","component---src-pages-index-js-20f4accd0ed20fe28911.js"],"component---src-templates-normal-page-js":["styles.5478f1c14286ecfac51c.css","styles-89fd2ae28bdf06750a71.js","commons-e8dca2748e39fa297292.js","component---src-templates-normal-page-js-fc5e8da66e25859a5b39.js"]}}